[
    {
        "flight": "destination",
        "country": "ShanghaiPVG",
        "code": "PVG"
    },
    {
        "flight": "destination",
        "country": "GuamGUM",
        "code": "GUM"
    },
    {
        "flight": "destination",
        "country": "FukuokaFUK",
        "code": "FUK"
    },
    {
        "flight": "destination",
        "country": "KitakyushuKKJ",
        "code": "KKJ"
    },
    {
        "flight": "destination",
        "country": "NagoyaNGO",
        "code": "NGO"
    },
    {
        "flight": "destination",
        "country": "OkinawaOKA",
        "code": "OKA"
    },
    {
        "flight": "destination",
        "country": "OsakaKIX",
        "code": "KIX"
    },
    {
        "flight": "destination",
        "country": "SapporoCTS",
        "code": "CTS"
    },
    {
        "flight": "destination",
        "country": "TokyoNRT",
        "code": "NRT"
    },
    {
        "flight": "destination",
        "country": "VientianeVTE",
        "code": "VTE"
    },
    {
        "flight": "destination",
        "country": "MacauMFM",
        "code": "MFM"
    },
    {
        "flight": "destination",
        "country": "Kota KinabaluBKI",
        "code": "BKI"
    },
    {
        "flight": "destination",
        "country": "Angeles CityCRK",
        "code": "CRK"
    },
    {
        "flight": "destination",
        "country": "CebuCEB",
        "code": "CEB"
    },
    {
        "flight": "destination",
        "country": "BusanPUS",
        "code": "PUS"
    },
    {
        "flight": "destination",
        "country": "Cheongju & DaejeonCJJ",
        "code": "CJJ"
    },
    {
        "flight": "destination",
        "country": "DaeguTAE",
        "code": "TAE"
    },
    {
        "flight": "destination",
        "country": "GunsanKUV",
        "code": "KUV"
    },
    {
        "flight": "destination",
        "country": "GwangjuKWJ",
        "code": "KWJ"
    },
    {
        "flight": "destination",
        "country": "Jeju CityCJU",
        "code": "CJU"
    },
    {
        "flight": "destination",
        "country": "PohangKPO",
        "code": "KPO"
    },
    {
        "flight": "destination",
        "country": "Sacheon / JinjuHIN",
        "code": "HIN"
    },
    {
        "flight": "destination",
        "country": "SeoulICN",
        "code": "ICN"
    },
    {
        "flight": "destination",
        "country": "SeoulGMP",
        "code": "GMP"
    },
    {
        "flight": "destination",
        "country": "UlsanUSN",
        "code": "USN"
    },
    {
        "flight": "destination",
        "country": "WonjuWJU",
        "code": "WJU"
    },
    {
        "flight": "destination",
        "country": "YeosuRSU",
        "code": "RSU"
    },
    {
        "flight": "destination",
        "country": "TaipeiTPE",
        "code": "TPE"
    },
    {
        "flight": "destination",
        "country": "BangkokBKK",
        "code": "BKK"
    },
    {
        "flight": "destination",
        "country": "PhuketHKT",
        "code": "HKT"
    },
    {
        "flight": "destination",
        "country": "Da NangDAD",
        "code": "DAD"
    },
    {
        "flight": "destination",
        "country": "Nha TrangCXR",
        "code": "CXR"
    },
    {
        "flight": "departure",
        "country": "ShanghaiPVG",
        "code": "PVG"
    },
    {
        "flight": "departure",
        "country": "GuamGUM",
        "code": "GUM"
    },
    {
        "flight": "departure",
        "country": "FukuokaFUK",
        "code": "FUK"
    },
    {
        "flight": "departure",
        "country": "KitakyushuKKJ",
        "code": "KKJ"
    },
    {
        "flight": "departure",
        "country": "NagoyaNGO",
        "code": "NGO"
    },
    {
        "flight": "departure",
        "country": "OkinawaOKA",
        "code": "OKA"
    },
    {
        "flight": "departure",
        "country": "OsakaKIX",
        "code": "KIX"
    },
    {
        "flight": "departure",
        "country": "SapporoCTS",
        "code": "CTS"
    },
    {
        "flight": "departure",
        "country": "TokyoNRT",
        "code": "NRT"
    },
    {
        "flight": "departure",
        "country": "VientianeVTE",
        "code": "VTE"
    },
    {
        "flight": "departure",
        "country": "MacauMFM",
        "code": "MFM"
    },
    {
        "flight": "departure",
        "country": "Kota KinabaluBKI",
        "code": "BKI"
    },
    {
        "flight": "departure",
        "country": "Angeles CityCRK",
        "code": "CRK"
    },
    {
        "flight": "departure",
        "country": "CebuCEB",
        "code": "CEB"
    },
    {
        "flight": "departure",
        "country": "BusanPUS",
        "code": "PUS"
    },
    {
        "flight": "departure",
        "country": "Cheongju & DaejeonCJJ",
        "code": "CJJ"
    },
    {
        "flight": "departure",
        "country": "DaeguTAE",
        "code": "TAE"
    },
    {
        "flight": "departure",
        "country": "GunsanKUV",
        "code": "KUV"
    },
    {
        "flight": "departure",
        "country": "GwangjuKWJ",
        "code": "KWJ"
    },
    {
        "flight": "departure",
        "country": "Jeju CityCJU",
        "code": "CJU"
    },
    {
        "flight": "departure",
        "country": "PohangKPO",
        "code": "KPO"
    },
    {
        "flight": "departure",
        "country": "Sacheon / JinjuHIN",
        "code": "HIN"
    },
    {
        "flight": "departure",
        "country": "SeoulICN",
        "code": "ICN"
    },
    {
        "flight": "departure",
        "country": "SeoulGMP",
        "code": "GMP"
    },
    {
        "flight": "departure",
        "country": "UlsanUSN",
        "code": "USN"
    },
    {
        "flight": "departure",
        "country": "WonjuWJU",
        "code": "WJU"
    },
    {
        "flight": "departure",
        "country": "YeosuRSU",
        "code": "RSU"
    },
    {
        "flight": "departure",
        "country": "TaipeiTPE",
        "code": "TPE"
    },
    {
        "flight": "departure",
        "country": "BangkokBKK",
        "code": "BKK"
    },
    {
        "flight": "departure",
        "country": "PhuketHKT",
        "code": "HKT"
    },
    {
        "flight": "departure",
        "country": "Da NangDAD",
        "code": "DAD"
    },
    {
        "flight": "departure",
        "country": "Nha TrangCXR",
        "code": "CXR"
    }
]