[
    {
        "flight": "destination",
        "country": "TiranaTIA",
        "code": "TIA"
    },
    {
        "flight": "destination",
        "country": "Buenos AiresEZE",
        "code": "EZE"
    },
    {
        "flight": "destination",
        "country": "GrazGRZ",
        "code": "GRZ"
    },
    {
        "flight": "destination",
        "country": "ViennaVIE",
        "code": "VIE"
    },
    {
        "flight": "destination",
        "country": "BrusselsBRU",
        "code": "BRU"
    },
    {
        "flight": "destination",
        "country": "SarajevoSJJ",
        "code": "SJJ"
    },
    {
        "flight": "destination",
        "country": "São PauloGRU",
        "code": "GRU"
    },
    {
        "flight": "destination",
        "country": "SofiaSOF",
        "code": "SOF"
    },
    {
        "flight": "destination",
        "country": "MontrealYUL",
        "code": "YUL"
    },
    {
        "flight": "destination",
        "country": "TorontoYYZ",
        "code": "YYZ"
    },
    {
        "flight": "destination",
        "country": "ShanghaiPVG",
        "code": "PVG"
    },
    {
        "flight": "destination",
        "country": "LarnacaLCA",
        "code": "LCA"
    },
    {
        "flight": "destination",
        "country": "PraguePRG",
        "code": "PRG"
    },
    {
        "flight": "destination",
        "country": "BillundBLL",
        "code": "BLL"
    },
    {
        "flight": "destination",
        "country": "CopenhagenCPH",
        "code": "CPH"
    },
    {
        "flight": "destination",
        "country": "CairoCAI",
        "code": "CAI"
    },
    {
        "flight": "destination",
        "country": "HurghadaHRG",
        "code": "HRG"
    },
    {
        "flight": "destination",
        "country": "TallinnTLL",
        "code": "TLL"
    },
    {
        "flight": "destination",
        "country": "KittiläKTT",
        "code": "KTT"
    },
    {
        "flight": "destination",
        "country": "BiarritzBIQ",
        "code": "BIQ"
    },
    {
        "flight": "destination",
        "country": "BordeauxBOD",
        "code": "BOD"
    },
    {
        "flight": "destination",
        "country": "MarseilleMRS",
        "code": "MRS"
    },
    {
        "flight": "destination",
        "country": "NantesNTE",
        "code": "NTE"
    },
    {
        "flight": "destination",
        "country": "NiceNCE",
        "code": "NCE"
    },
    {
        "flight": "destination",
        "country": "ParisCDG",
        "code": "CDG"
    },
    {
        "flight": "destination",
        "country": "BerlinBER",
        "code": "BER"
    },
    {
        "flight": "destination",
        "country": "BremenBRE",
        "code": "BRE"
    },
    {
        "flight": "destination",
        "country": "DresdenDRS",
        "code": "DRS"
    },
    {
        "flight": "destination",
        "country": "DüsseldorfDUS",
        "code": "DUS"
    },
    {
        "flight": "destination",
        "country": "FrankfurtFRA",
        "code": "FRA"
    },
    {
        "flight": "destination",
        "country": "HamburgHAM",
        "code": "HAM"
    },
    {
        "flight": "destination",
        "country": "HanoverHAJ",
        "code": "HAJ"
    },
    {
        "flight": "destination",
        "country": "MunichMUC",
        "code": "MUC"
    },
    {
        "flight": "destination",
        "country": "NurembergNUE",
        "code": "NUE"
    },
    {
        "flight": "destination",
        "country": "StuttgartSTR",
        "code": "STR"
    },
    {
        "flight": "destination",
        "country": "Westerland / SyltGWT",
        "code": "GWT"
    },
    {
        "flight": "destination",
        "country": "AthensATH",
        "code": "ATH"
    },
    {
        "flight": "destination",
        "country": "Corfu (Kerkyra)CFU",
        "code": "CFU"
    },
    {
        "flight": "destination",
        "country": "Heraklion (Crete)HER",
        "code": "HER"
    },
    {
        "flight": "destination",
        "country": "KalamataKLX",
        "code": "KLX"
    },
    {
        "flight": "destination",
        "country": "KosKGS",
        "code": "KGS"
    },
    {
        "flight": "destination",
        "country": "MykonosJMK",
        "code": "JMK"
    },
    {
        "flight": "destination",
        "country": "RhodesRHO",
        "code": "RHO"
    },
    {
        "flight": "destination",
        "country": "SantoriniJTR",
        "code": "JTR"
    },
    {
        "flight": "destination",
        "country": "ThessalonikiSKG",
        "code": "SKG"
    },
    {
        "flight": "destination",
        "country": "Zakynthos IslandZTH",
        "code": "ZTH"
    },
    {
        "flight": "destination",
        "country": "Hong KongHKG",
        "code": "HKG"
    },
    {
        "flight": "destination",
        "country": "BudapestBUD",
        "code": "BUD"
    },
    {
        "flight": "destination",
        "country": "MumbaiBOM",
        "code": "BOM"
    },
    {
        "flight": "destination",
        "country": "New DelhiDEL",
        "code": "DEL"
    },
    {
        "flight": "destination",
        "country": "CorkORK",
        "code": "ORK"
    },
    {
        "flight": "destination",
        "country": "DublinDUB",
        "code": "DUB"
    },
    {
        "flight": "destination",
        "country": "Tel AvivTLV",
        "code": "TLV"
    },
    {
        "flight": "destination",
        "country": "BolognaBLQ",
        "code": "BLQ"
    },
    {
        "flight": "destination",
        "country": "BrindisiBDS",
        "code": "BDS"
    },
    {
        "flight": "destination",
        "country": "CataniaCTA",
        "code": "CTA"
    },
    {
        "flight": "destination",
        "country": "FlorenceFLR",
        "code": "FLR"
    },
    {
        "flight": "destination",
        "country": "Milan (Malpensa)MXP",
        "code": "MXP"
    },
    {
        "flight": "destination",
        "country": "NaplesNAP",
        "code": "NAP"
    },
    {
        "flight": "destination",
        "country": "Olbia (Sardinia)OLB",
        "code": "OLB"
    },
    {
        "flight": "destination",
        "country": "PalermoPMO",
        "code": "PMO"
    },
    {
        "flight": "destination",
        "country": "Rome (Fiumicino)FCO",
        "code": "FCO"
    },
    {
        "flight": "destination",
        "country": "Venice Marco PoloVCE",
        "code": "VCE"
    },
    {
        "flight": "destination",
        "country": "TokyoNRT",
        "code": "NRT"
    },
    {
        "flight": "destination",
        "country": "BeirutBEY",
        "code": "BEY"
    },
    {
        "flight": "destination",
        "country": "VilniusVNO",
        "code": "VNO"
    },
    {
        "flight": "destination",
        "country": "Luxembourg CityLUX",
        "code": "LUX"
    },
    {
        "flight": "destination",
        "country": "MaltaMLA",
        "code": "MLA"
    },
    {
        "flight": "destination",
        "country": "MarrakechRAK",
        "code": "RAK"
    },
    {
        "flight": "destination",
        "country": "AmsterdamAMS",
        "code": "AMS"
    },
    {
        "flight": "destination",
        "country": "OsloOSL",
        "code": "OSL"
    },
    {
        "flight": "destination",
        "country": "GdańskGDN",
        "code": "GDN"
    },
    {
        "flight": "destination",
        "country": "KrakowKRK",
        "code": "KRK"
    },
    {
        "flight": "destination",
        "country": "WarsawWAW",
        "code": "WAW"
    },
    {
        "flight": "destination",
        "country": "WrocławWRO",
        "code": "WRO"
    },
    {
        "flight": "destination",
        "country": "FaroFAO",
        "code": "FAO"
    },
    {
        "flight": "destination",
        "country": "Funchal (Madeira)FNC",
        "code": "FNC"
    },
    {
        "flight": "destination",
        "country": "LisbonLIS",
        "code": "LIS"
    },
    {
        "flight": "destination",
        "country": "Ponta DelgadaPDL",
        "code": "PDL"
    },
    {
        "flight": "destination",
        "country": "PortoOPO",
        "code": "OPO"
    },
    {
        "flight": "destination",
        "country": "BucharestOTP",
        "code": "OTP"
    },
    {
        "flight": "destination",
        "country": "Cluj-NapocaCLJ",
        "code": "CLJ"
    },
    {
        "flight": "destination",
        "country": "BelgradeBEG",
        "code": "BEG"
    },
    {
        "flight": "destination",
        "country": "PristinaPRN",
        "code": "PRN"
    },
    {
        "flight": "destination",
        "country": "SingaporeSIN",
        "code": "SIN"
    },
    {
        "flight": "destination",
        "country": "KošiceKSC",
        "code": "KSC"
    },
    {
        "flight": "destination",
        "country": "LjubljanaLJU",
        "code": "LJU"
    },
    {
        "flight": "destination",
        "country": "JohannesburgJNB",
        "code": "JNB"
    },
    {
        "flight": "destination",
        "country": "AlicanteALC",
        "code": "ALC"
    },
    {
        "flight": "destination",
        "country": "BarcelonaBCN",
        "code": "BCN"
    },
    {
        "flight": "destination",
        "country": "IbizaIBZ",
        "code": "IBZ"
    },
    {
        "flight": "destination",
        "country": "MadridMAD",
        "code": "MAD"
    },
    {
        "flight": "destination",
        "country": "MálagaAGP",
        "code": "AGP"
    },
    {
        "flight": "destination",
        "country": "Menorca (Mahon)MAH",
        "code": "MAH"
    },
    {
        "flight": "destination",
        "country": "Palma de MallorcaPMI",
        "code": "PMI"
    },
    {
        "flight": "destination",
        "country": "ValenciaVLC",
        "code": "VLC"
    },
    {
        "flight": "destination",
        "country": "GothenburgGOT",
        "code": "GOT"
    },
    {
        "flight": "destination",
        "country": "Stockholm (Arlanda)ARN",
        "code": "ARN"
    },
    {
        "flight": "destination",
        "country": "GenevaGVA",
        "code": "GVA"
    },
    {
        "flight": "destination",
        "country": "ZürichZRH",
        "code": "ZRH"
    },
    {
        "flight": "destination",
        "country": "BangkokBKK",
        "code": "BKK"
    },
    {
        "flight": "destination",
        "country": "DjerbaDJE",
        "code": "DJE"
    },
    {
        "flight": "destination",
        "country": "AntalyaAYT",
        "code": "AYT"
    },
    {
        "flight": "destination",
        "country": "DubaiDXB",
        "code": "DXB"
    },
    {
        "flight": "destination",
        "country": "BirminghamBHX",
        "code": "BHX"
    },
    {
        "flight": "destination",
        "country": "BristolBRS",
        "code": "BRS"
    },
    {
        "flight": "destination",
        "country": "London CityLCY",
        "code": "LCY"
    },
    {
        "flight": "destination",
        "country": "London GatwickLGW",
        "code": "LGW"
    },
    {
        "flight": "destination",
        "country": "London HeathrowLHR",
        "code": "LHR"
    },
    {
        "flight": "destination",
        "country": "ManchesterMAN",
        "code": "MAN"
    },
    {
        "flight": "destination",
        "country": "BostonBOS",
        "code": "BOS"
    },
    {
        "flight": "destination",
        "country": "ChicagoORD",
        "code": "ORD"
    },
    {
        "flight": "destination",
        "country": "Los AngelesLAX",
        "code": "LAX"
    },
    {
        "flight": "destination",
        "country": "MiamiMIA",
        "code": "MIA"
    },
    {
        "flight": "destination",
        "country": "New YorkEWR",
        "code": "EWR"
    },
    {
        "flight": "destination",
        "country": "New York CityJFK",
        "code": "JFK"
    },
    {
        "flight": "destination",
        "country": "San FranciscoSFO",
        "code": "SFO"
    },
    {
        "flight": "destination",
        "country": "WashingtonIAD",
        "code": "IAD"
    },
    {
        "flight": "departure",
        "country": "TiranaTIA",
        "code": "TIA"
    },
    {
        "flight": "departure",
        "country": "Buenos AiresEZE",
        "code": "EZE"
    },
    {
        "flight": "departure",
        "country": "GrazGRZ",
        "code": "GRZ"
    },
    {
        "flight": "departure",
        "country": "ViennaVIE",
        "code": "VIE"
    },
    {
        "flight": "departure",
        "country": "BrusselsBRU",
        "code": "BRU"
    },
    {
        "flight": "departure",
        "country": "SarajevoSJJ",
        "code": "SJJ"
    },
    {
        "flight": "departure",
        "country": "São PauloGRU",
        "code": "GRU"
    },
    {
        "flight": "departure",
        "country": "SofiaSOF",
        "code": "SOF"
    },
    {
        "flight": "departure",
        "country": "MontrealYUL",
        "code": "YUL"
    },
    {
        "flight": "departure",
        "country": "TorontoYYZ",
        "code": "YYZ"
    },
    {
        "flight": "departure",
        "country": "ShanghaiPVG",
        "code": "PVG"
    },
    {
        "flight": "departure",
        "country": "LarnacaLCA",
        "code": "LCA"
    },
    {
        "flight": "departure",
        "country": "PraguePRG",
        "code": "PRG"
    },
    {
        "flight": "departure",
        "country": "BillundBLL",
        "code": "BLL"
    },
    {
        "flight": "departure",
        "country": "CopenhagenCPH",
        "code": "CPH"
    },
    {
        "flight": "departure",
        "country": "CairoCAI",
        "code": "CAI"
    },
    {
        "flight": "departure",
        "country": "HurghadaHRG",
        "code": "HRG"
    },
    {
        "flight": "departure",
        "country": "TallinnTLL",
        "code": "TLL"
    },
    {
        "flight": "departure",
        "country": "KittiläKTT",
        "code": "KTT"
    },
    {
        "flight": "departure",
        "country": "BiarritzBIQ",
        "code": "BIQ"
    },
    {
        "flight": "departure",
        "country": "BordeauxBOD",
        "code": "BOD"
    },
    {
        "flight": "departure",
        "country": "MarseilleMRS",
        "code": "MRS"
    },
    {
        "flight": "departure",
        "country": "NantesNTE",
        "code": "NTE"
    },
    {
        "flight": "departure",
        "country": "NiceNCE",
        "code": "NCE"
    },
    {
        "flight": "departure",
        "country": "ParisCDG",
        "code": "CDG"
    },
    {
        "flight": "departure",
        "country": "BerlinBER",
        "code": "BER"
    },
    {
        "flight": "departure",
        "country": "BremenBRE",
        "code": "BRE"
    },
    {
        "flight": "departure",
        "country": "DresdenDRS",
        "code": "DRS"
    },
    {
        "flight": "departure",
        "country": "DüsseldorfDUS",
        "code": "DUS"
    },
    {
        "flight": "departure",
        "country": "FrankfurtFRA",
        "code": "FRA"
    },
    {
        "flight": "departure",
        "country": "HamburgHAM",
        "code": "HAM"
    },
    {
        "flight": "departure",
        "country": "HanoverHAJ",
        "code": "HAJ"
    },
    {
        "flight": "departure",
        "country": "MunichMUC",
        "code": "MUC"
    },
    {
        "flight": "departure",
        "country": "NurembergNUE",
        "code": "NUE"
    },
    {
        "flight": "departure",
        "country": "StuttgartSTR",
        "code": "STR"
    },
    {
        "flight": "departure",
        "country": "Westerland / SyltGWT",
        "code": "GWT"
    },
    {
        "flight": "departure",
        "country": "AthensATH",
        "code": "ATH"
    },
    {
        "flight": "departure",
        "country": "Corfu (Kerkyra)CFU",
        "code": "CFU"
    },
    {
        "flight": "departure",
        "country": "Heraklion (Crete)HER",
        "code": "HER"
    },
    {
        "flight": "departure",
        "country": "KalamataKLX",
        "code": "KLX"
    },
    {
        "flight": "departure",
        "country": "KosKGS",
        "code": "KGS"
    },
    {
        "flight": "departure",
        "country": "MykonosJMK",
        "code": "JMK"
    },
    {
        "flight": "departure",
        "country": "RhodesRHO",
        "code": "RHO"
    },
    {
        "flight": "departure",
        "country": "SantoriniJTR",
        "code": "JTR"
    },
    {
        "flight": "departure",
        "country": "ThessalonikiSKG",
        "code": "SKG"
    },
    {
        "flight": "departure",
        "country": "Zakynthos IslandZTH",
        "code": "ZTH"
    },
    {
        "flight": "departure",
        "country": "Hong KongHKG",
        "code": "HKG"
    },
    {
        "flight": "departure",
        "country": "BudapestBUD",
        "code": "BUD"
    },
    {
        "flight": "departure",
        "country": "MumbaiBOM",
        "code": "BOM"
    },
    {
        "flight": "departure",
        "country": "New DelhiDEL",
        "code": "DEL"
    },
    {
        "flight": "departure",
        "country": "CorkORK",
        "code": "ORK"
    },
    {
        "flight": "departure",
        "country": "DublinDUB",
        "code": "DUB"
    },
    {
        "flight": "departure",
        "country": "Tel AvivTLV",
        "code": "TLV"
    },
    {
        "flight": "departure",
        "country": "BolognaBLQ",
        "code": "BLQ"
    },
    {
        "flight": "departure",
        "country": "BrindisiBDS",
        "code": "BDS"
    },
    {
        "flight": "departure",
        "country": "CataniaCTA",
        "code": "CTA"
    },
    {
        "flight": "departure",
        "country": "FlorenceFLR",
        "code": "FLR"
    },
    {
        "flight": "departure",
        "country": "Milan (Malpensa)MXP",
        "code": "MXP"
    },
    {
        "flight": "departure",
        "country": "NaplesNAP",
        "code": "NAP"
    },
    {
        "flight": "departure",
        "country": "Olbia (Sardinia)OLB",
        "code": "OLB"
    },
    {
        "flight": "departure",
        "country": "PalermoPMO",
        "code": "PMO"
    },
    {
        "flight": "departure",
        "country": "Rome (Fiumicino)FCO",
        "code": "FCO"
    },
    {
        "flight": "departure",
        "country": "Venice Marco PoloVCE",
        "code": "VCE"
    },
    {
        "flight": "departure",
        "country": "TokyoNRT",
        "code": "NRT"
    },
    {
        "flight": "departure",
        "country": "BeirutBEY",
        "code": "BEY"
    },
    {
        "flight": "departure",
        "country": "VilniusVNO",
        "code": "VNO"
    },
    {
        "flight": "departure",
        "country": "Luxembourg CityLUX",
        "code": "LUX"
    },
    {
        "flight": "departure",
        "country": "MaltaMLA",
        "code": "MLA"
    },
    {
        "flight": "departure",
        "country": "MarrakechRAK",
        "code": "RAK"
    },
    {
        "flight": "departure",
        "country": "AmsterdamAMS",
        "code": "AMS"
    },
    {
        "flight": "departure",
        "country": "OsloOSL",
        "code": "OSL"
    },
    {
        "flight": "departure",
        "country": "GdańskGDN",
        "code": "GDN"
    },
    {
        "flight": "departure",
        "country": "KrakowKRK",
        "code": "KRK"
    },
    {
        "flight": "departure",
        "country": "WarsawWAW",
        "code": "WAW"
    },
    {
        "flight": "departure",
        "country": "WrocławWRO",
        "code": "WRO"
    },
    {
        "flight": "departure",
        "country": "FaroFAO",
        "code": "FAO"
    },
    {
        "flight": "departure",
        "country": "Funchal (Madeira)FNC",
        "code": "FNC"
    },
    {
        "flight": "departure",
        "country": "LisbonLIS",
        "code": "LIS"
    },
    {
        "flight": "departure",
        "country": "Ponta DelgadaPDL",
        "code": "PDL"
    },
    {
        "flight": "departure",
        "country": "PortoOPO",
        "code": "OPO"
    },
    {
        "flight": "departure",
        "country": "BucharestOTP",
        "code": "OTP"
    },
    {
        "flight": "departure",
        "country": "Cluj-NapocaCLJ",
        "code": "CLJ"
    },
    {
        "flight": "departure",
        "country": "BelgradeBEG",
        "code": "BEG"
    },
    {
        "flight": "departure",
        "country": "PristinaPRN",
        "code": "PRN"
    },
    {
        "flight": "departure",
        "country": "SingaporeSIN",
        "code": "SIN"
    },
    {
        "flight": "departure",
        "country": "KošiceKSC",
        "code": "KSC"
    },
    {
        "flight": "departure",
        "country": "LjubljanaLJU",
        "code": "LJU"
    },
    {
        "flight": "departure",
        "country": "JohannesburgJNB",
        "code": "JNB"
    },
    {
        "flight": "departure",
        "country": "AlicanteALC",
        "code": "ALC"
    },
    {
        "flight": "departure",
        "country": "BarcelonaBCN",
        "code": "BCN"
    },
    {
        "flight": "departure",
        "country": "IbizaIBZ",
        "code": "IBZ"
    },
    {
        "flight": "departure",
        "country": "MadridMAD",
        "code": "MAD"
    },
    {
        "flight": "departure",
        "country": "MálagaAGP",
        "code": "AGP"
    },
    {
        "flight": "departure",
        "country": "Menorca (Mahon)MAH",
        "code": "MAH"
    },
    {
        "flight": "departure",
        "country": "Palma de MallorcaPMI",
        "code": "PMI"
    },
    {
        "flight": "departure",
        "country": "ValenciaVLC",
        "code": "VLC"
    },
    {
        "flight": "departure",
        "country": "GothenburgGOT",
        "code": "GOT"
    },
    {
        "flight": "departure",
        "country": "Stockholm (Arlanda)ARN",
        "code": "ARN"
    },
    {
        "flight": "departure",
        "country": "GenevaGVA",
        "code": "GVA"
    },
    {
        "flight": "departure",
        "country": "ZürichZRH",
        "code": "ZRH"
    },
    {
        "flight": "departure",
        "country": "BangkokBKK",
        "code": "BKK"
    },
    {
        "flight": "departure",
        "country": "DjerbaDJE",
        "code": "DJE"
    },
    {
        "flight": "departure",
        "country": "AntalyaAYT",
        "code": "AYT"
    },
    {
        "flight": "departure",
        "country": "DubaiDXB",
        "code": "DXB"
    },
    {
        "flight": "departure",
        "country": "BirminghamBHX",
        "code": "BHX"
    },
    {
        "flight": "departure",
        "country": "BristolBRS",
        "code": "BRS"
    },
    {
        "flight": "departure",
        "country": "London CityLCY",
        "code": "LCY"
    },
    {
        "flight": "departure",
        "country": "London GatwickLGW",
        "code": "LGW"
    },
    {
        "flight": "departure",
        "country": "London HeathrowLHR",
        "code": "LHR"
    },
    {
        "flight": "departure",
        "country": "ManchesterMAN",
        "code": "MAN"
    },
    {
        "flight": "departure",
        "country": "BostonBOS",
        "code": "BOS"
    },
    {
        "flight": "departure",
        "country": "ChicagoORD",
        "code": "ORD"
    },
    {
        "flight": "departure",
        "country": "Los AngelesLAX",
        "code": "LAX"
    },
    {
        "flight": "departure",
        "country": "MiamiMIA",
        "code": "MIA"
    },
    {
        "flight": "departure",
        "country": "New YorkEWR",
        "code": "EWR"
    },
    {
        "flight": "departure",
        "country": "New York CityJFK",
        "code": "JFK"
    },
    {
        "flight": "departure",
        "country": "San FranciscoSFO",
        "code": "SFO"
    },
    {
        "flight": "departure",
        "country": "WashingtonIAD",
        "code": "IAD"
    }
]